{"original_file_path": "SAP_SFTP/DKSH_TW/CUSTOMER_3/FOLDER_10/DN800018251920240708123641.csv", "document_type": "order", "po_number": null, "items": [{"Column_1": "SD005", "Column_2": "20240708123641", "Column_3": "8000182519", "Column_4": "000001", "Column_5": "20240709", "Column_6": "TW00206666", "Column_7": "?????", "Column_8": "0972808094", "Column_9": "351", "Column_10": "??????", "Column_11": "?????35?", "Column_12": "109003???PPG240705G001?????", "Column_13": "3100", "Column_14": "3123042", "Column_15": "FWHB", "Column_16": "18", "Column_17": "PAK", "Column_18": "", "Column_19": "???????? 0972808094", "Column_20": "???", "Column_21": "", "Column_22": "", "Column_23": "", "Column_24": "", "Column_25": "0", "Column_26": "", "Column_27": ""}, {"Column_1": "SD005", "Column_2": "20240708123641", "Column_3": "8000182519", "Column_4": "000002", "Column_5": "20240709", "Column_6": "TW00206666", "Column_7": "?????", "Column_8": "0972808094", "Column_9": "351", "Column_10": "??????", "Column_11": "?????35?", "Column_12": "109003???PPG240705G001?????", "Column_13": "3100", "Column_14": "3123043", "Column_15": "FWHB", "Column_16": "144", "Column_17": "PAK", "Column_18": "", "Column_19": "???????? 0972808094", "Column_20": "???", "Column_21": "", "Column_22": "", "Column_23": "", "Column_24": "", "Column_25": "0", "Column_26": "", "Column_27": ""}, {"Column_1": "SD005", "Column_2": "20240708123641", "Column_3": "8000182519", "Column_4": "000003", "Column_5": "20240709", "Column_6": "TW00206666", "Column_7": "?????", "Column_8": "0972808094", "Column_9": "351", "Column_10": "??????", "Column_11": "?????35?", "Column_12": "109003???PPG240705G001?????", "Column_13": "3100", "Column_14": "3123044", "Column_15": "FWHB", "Column_16": "196", "Column_17": "PAK", "Column_18": "", "Column_19": "???????? 0972808094", "Column_20": "???", "Column_21": "", "Column_22": "", "Column_23": "", "Column_24": "", "Column_25": "0", "Column_26": "", "Column_27": ""}, {"Column_1": "SD005", "Column_2": "20240708123641", "Column_3": "8000182519", "Column_4": "000004", "Column_5": "20240709", "Column_6": "TW00206666", "Column_7": "?????", "Column_8": "0972808094", "Column_9": "351", "Column_10": "??????", "Column_11": "?????35?", "Column_12": "109003???PPG240705G001?????", "Column_13": "3100", "Column_14": "3123045", "Column_15": "FWHB", "Column_16": "45", "Column_17": "PAK", "Column_18": "", "Column_19": "???????? 0972808094", "Column_20": "???", "Column_21": "", "Column_22": "", "Column_23": "", "Column_24": "", "Column_25": "0", "Column_26": "", "Column_27": ""}, {"Column_1": "SD005", "Column_2": "20240708123641", "Column_3": "8000182519", "Column_4": "000005", "Column_5": "20240709", "Column_6": "TW00206666", "Column_7": "?????", "Column_8": "0972808094", "Column_9": "351", "Column_10": "??????", "Column_11": "?????35?", "Column_12": "109003???PPG240705G001?????", "Column_13": "3100", "Column_14": "3123046", "Column_15": "FWHB", "Column_16": "27", "Column_17": "PAK", "Column_18": "", "Column_19": "???????? 0972808094", "Column_20": "???", "Column_21": "", "Column_22": "", "Column_23": "", "Column_24": "", "Column_25": "0", "Column_26": "", "Column_27": ""}, {"Column_1": "SD005", "Column_2": "20240708123641", "Column_3": "8000182519", "Column_4": "000006", "Column_5": "20240709", "Column_6": "TW00206666", "Column_7": "?????", "Column_8": "0972808094", "Column_9": "351", "Column_10": "??????", "Column_11": "?????35?", "Column_12": "109003???PPG240705G001?????", "Column_13": "3100", "Column_14": "3123047", "Column_15": "FWHB", "Column_16": "60", "Column_17": "PAK", "Column_18": "", "Column_19": "???????? 0972808094", "Column_20": "???", "Column_21": "", "Column_22": "", "Column_23": "", "Column_24": "", "Column_25": "0", "Column_26": "", "Column_27": ""}, {"Column_1": "SD005", "Column_2": "20240708123641", "Column_3": "8000182519", "Column_4": "000007", "Column_5": "20240709", "Column_6": "TW00206666", "Column_7": "?????", "Column_8": "0972808094", "Column_9": "351", "Column_10": "??????", "Column_11": "?????35?", "Column_12": "109003???PPG240705G001?????", "Column_13": "3100", "Column_14": "3123048", "Column_15": "FWHB", "Column_16": "184", "Column_17": "PAK", "Column_18": "", "Column_19": "???????? 0972808094", "Column_20": "???", "Column_21": "", "Column_22": "", "Column_23": "", "Column_24": "", "Column_25": "0", "Column_26": "", "Column_27": ""}, {"Column_1": "SD005", "Column_2": "20240708123641", "Column_3": "8000182519", "Column_4": "000008", "Column_5": "20240709", "Column_6": "TW00206666", "Column_7": "?????", "Column_8": "0972808094", "Column_9": "351", "Column_10": "??????", "Column_11": "?????35?", "Column_12": "109003???PPG240705G001?????", "Column_13": "3100", "Column_14": "3123049", "Column_15": "FWHB", "Column_16": "336", "Column_17": "PAK", "Column_18": "", "Column_19": "???????? 0972808094", "Column_20": "???", "Column_21": "", "Column_22": "", "Column_23": "", "Column_24": "", "Column_25": "0", "Column_26": "", "Column_27": ""}, {"Column_1": "SD005", "Column_2": "20240708123641", "Column_3": "8000182519", "Column_4": "000009", "Column_5": "20240709", "Column_6": "TW00206666", "Column_7": "?????", "Column_8": "0972808094", "Column_9": "351", "Column_10": "??????", "Column_11": "?????35?", "Column_12": "109003???PPG240705G001?????", "Column_13": "3100", "Column_14": "3123144", "Column_15": "FWHB", "Column_16": "26", "Column_17": "CAR", "Column_18": "", "Column_19": "???????? 0972808094", "Column_20": "???", "Column_21": "", "Column_22": "", "Column_23": "", "Column_24": "", "Column_25": "0", "Column_26": "", "Column_27": ""}, {"Column_1": "SD005", "Column_2": "20240708123641", "Column_3": "8000182519", "Column_4": "000010", "Column_5": "20240709", "Column_6": "TW00206666", "Column_7": "?????", "Column_8": "0972808094", "Column_9": "351", "Column_10": "??????", "Column_11": "?????35?", "Column_12": "109003???PPG240705G001?????", "Column_13": "3100", "Column_14": "3110292", "Column_15": "FWHB", "Column_16": "276", "Column_17": "PAK", "Column_18": "", "Column_19": "???????? 0972808094", "Column_20": "???", "Column_21": "", "Column_22": "", "Column_23": "", "Column_24": "", "Column_25": "0", "Column_26": "", "Column_27": ""}, {"Column_1": "SD005", "Column_2": "20240708123641", "Column_3": "8000182519", "Column_4": "000011", "Column_5": "20240709", "Column_6": "TW00206666", "Column_7": "?????", "Column_8": "0972808094", "Column_9": "351", "Column_10": "??????", "Column_11": "?????35?", "Column_12": "109003???PPG240705G001?????", "Column_13": "3100", "Column_14": "3123038", "Column_15": "FWHB", "Column_16": "42", "Column_17": "PAK", "Column_18": "", "Column_19": "???????? 0972808094", "Column_20": "???", "Column_21": "", "Column_22": "", "Column_23": "", "Column_24": "", "Column_25": "0", "Column_26": "", "Column_27": ""}, {"Column_1": "SD005", "Column_2": "20240708123641", "Column_3": "8000182519", "Column_4": "000012", "Column_5": "20240709", "Column_6": "TW00206666", "Column_7": "?????", "Column_8": "0972808094", "Column_9": "351", "Column_10": "??????", "Column_11": "?????35?", "Column_12": "109003???PPG240705G001?????", "Column_13": "3100", "Column_14": "3123050", "Column_15": "FWHB", "Column_16": "48", "Column_17": "PAK", "Column_18": "", "Column_19": "???????? 0972808094", "Column_20": "???", "Column_21": "", "Column_22": "", "Column_23": "", "Column_24": "", "Column_25": "0", "Column_26": "", "Column_27": ""}, {"Column_1": "SD005", "Column_2": "20240708123641", "Column_3": "8000182519", "Column_4": "000013", "Column_5": "20240709", "Column_6": "TW00206666", "Column_7": "?????", "Column_8": "0972808094", "Column_9": "351", "Column_10": "??????", "Column_11": "?????35?", "Column_12": "109003???PPG240705G001?????", "Column_13": "3100", "Column_14": "3123051", "Column_15": "FWHB", "Column_16": "12", "Column_17": "PAK", "Column_18": "", "Column_19": "???????? 0972808094", "Column_20": "???", "Column_21": "", "Column_22": "", "Column_23": "", "Column_24": "", "Column_25": "0", "Column_26": "", "Column_27": ""}], "metadata": {}, "step_status": "1", "messages": null, "capacity": "2.58 KB", "step_detail": [{"step": {"workflowStepId": "0197e455-de5a-71d1-8428-6f10e4152f80", "stepName": "TEMPLATE_FILE_PARSE", "stepOrder": 1, "stepConfiguration": []}, "config_api": [{"stepId": "0197e455-de5a-71d1-8428-6f10e4152f80", "configId": "0197e455-deab-783d-97dd-7e7fcc368f11", "templateFileParse": {"id": "019979f0-c41e-7837-a157-dd15748de42e", "code": "CSV_003_TEMPLATE", "extension": "CSV"}}], "metadata_api": [{"url": "/api/workflow/step/start", "request": {"sessionId": "01999d8e-0baf-719c-acb7-69497c67e539", "stepId": "0197e455-de5a-71d1-8428-6f10e4152f80"}, "response": {"workflowHistoryId": "01999d8e-0dcb-7b62-ab6a-fe77d605c080", "status": "PROCESSING"}}, {"url": "/api/workflow/step/finish", "request": {"workflowHistoryId": "01999d8e-0dcb-7b62-ab6a-fe77d605c080", "code": "1", "message": "", "dataInput": "input_data", "dataOutput": "workflow-node-materialized/4f7bb6ac-81f1-4654-be15-2114e7d03a75/TEMPLATE_FILE_PARSE/DN800018251920240708123641.json"}, "response": {"workflowHistoryId": "01999d8e-0dcb-7b62-ab6a-fe77d605c080", "status": "SUCCESS"}}]}], "workflow_detail": {"filter_api": {"id": "0197e455-de48-74e1-8321-56d759a13b7f", "name": "DKSH Taiwan - Customer 3 - Folder 10 - CSV", "status": "ACTIVE", "isMasterDataWorkflow": false, "sapMasterData": false, "customerId": "0197e3f6-acb2-7347-b30c-e8cc2848598c", "workflowSteps": [{"workflowStepId": "0197e455-de5a-71d1-8428-6f10e4152f80", "stepName": "TEMPLATE_FILE_PARSE", "stepOrder": 1, "stepConfiguration": []}, {"workflowStepId": "0198cff4-1217-7e4a-8777-f95d13847d7f", "stepName": "TEMPLATE_FORMAT_VALIDATION", "stepOrder": 2, "stepConfiguration": []}, {"workflowStepId": "af353c09-fefb-4f9e-84cc-9f6f3dd23680", "stepName": "TEMPLATE_DATA_MAPPING", "stepOrder": 3, "stepConfiguration": []}]}, "metadata_api": [{"url": "/api/workflow/session/start", "request": {"workflowId": "0197e455-de48-74e1-8321-56d759a13b7f", "celeryId": "4f7bb6ac-81f1-4654-be15-2114e7d03a75", "filePath": "SAP_SFTP/DKSH_TW/CUSTOMER_3/FOLDER_10/DN800018251920240708123641.csv"}, "response": {"id": "01999d8e-0baf-719c-acb7-69497c67e539", "status": "PROCESSING"}}]}, "json_output": "workflow-node-materialized/4f7bb6ac-81f1-4654-be15-2114e7d03a75/TEMPLATE_FILE_PARSE/DN800018251920240708123641.json"}